{
  "$schema": "https://typedoc.org/schema.json",
  "plugin": ["typedoc-plugin-markdown", "typedoc-plugin-frontmatter"],
  "entryPoints": [
    "src/core/index.ts",
    "src/adapters/codecs/seroval.ts",
    "src/adapters/codecs/zod.ts",
    "src/adapters/backends/idb.ts",
    "src/adapters/backends/async-storage.ts",
    "src/adapters/backends/mmkv.ts",
    "src/adapters/backends/secure-store.ts",
    "src/adapters/backends/encrypted.ts",
    "src/adapters/backends/compressed.ts",
    "src/adapters/backends/node-fs.ts",
    "src/adapters/transport/crosstab.ts",
    "src/adapters/sources/tanstack-store.ts",
    "src/adapters/sources/zustand.ts",
    "src/adapters/sources/jotai.ts",
    "src/adapters/sources/valtio.ts",
    "src/adapters/sources/mobx.ts",
    "src/adapters/sources/pinia.ts",
    "src/adapters/sources/redux.ts",
    "src/adapters/frameworks/react.ts",
    "src/adapters/frameworks/solid.ts",
    "src/adapters/frameworks/vue.ts",
    "src/adapters/frameworks/svelte.ts",
    "src/adapters/frameworks/svelte-store.ts",
    "src/adapters/frameworks/angular.ts",
    "src/adapters/frameworks/preact.ts"
  ],
  "cleanOutputDir": false,
  "outputs": [
    {
      "name": "markdown",
      "path": "apps/docs/content/reference/api"
    }
  ],
  "router": "module",
  "publicPath": "/reference/api/",
  "preserveAnchorCasing": true,
  "fileExtension": ".mdx",
  "entryFileName": "_typedoc-entry.mdx",
  "modulesFileName": "_typedoc-modules.mdx",
  "flattenOutputFiles": true,
  "useCodeBlocks": true,
  "hidePageHeader": true,
  "hideBreadcrumbs": true,
  "indexFormat": "table",
  "parametersFormat": "table",
  "interfacePropertiesFormat": "table",
  "classPropertiesFormat": "table",
  "typeDeclarationFormat": "table",
  "name": "@stainless-code/persist",
  "includeVersion": true,
  "readme": "none",
  "entryPointStrategy": "resolve",
  "categorizeByGroup": false,
  "sort": ["source-order"],
  "visibilityFilters": {},
  "intentionallyNotExported": [],
  "treatWarningsAsErrors": true,
  "treatValidationWarningsAsErrors": true,
  "validation": {
    "notExported": true,
    "invalidLink": true,
    "invalidPath": true,
    "rewrittenLink": true
  },
  "excludePrivate": true,
  "excludeInternal": true,
  "disableSources": false,
  "sourceLinkTemplate": "https://github.com/stainless-code/persist/blob/{gitRevision}/{path}#L{line}",
  "gitRevision": "main",
  "logLevel": "Info",
  "frontmatterGlobals": {
    "search": {
      "tags": ["api", "reference"]
    }
  }
}
